printly/__init__.py
printly/const.py
printly/print.py
printly/py.typed
printly/style.py
printly/types.py
printly/validate.py
printly-0.5.0.dist-info/licenses/LICENSE
printly-0.5.0.dist-info/METADATA
printly-0.5.0.dist-info/WHEEL
printly-0.5.0.dist-info/top_level.txt
printly-0.5.0.dist-info/RECORD
