Metadata-Version: 2.4
Name: printly
Version: 0.5.0
Summary: Printly is a Python library that enhances the built-in print function with direct text styling: foreground color, background color, and font styles.
Author-email: "Haripo Wesley T." <haripowesleyt@proton.me>
Maintainer-email: "Haripo Wesley T." <haripowesleyt@proton.me>
License: MIT License
Project-URL: Homepage, https://github.com/haripowesleyt/printly
Project-URL: Issues, https://github.com/haripowesleyt/printly/issues
Project-URL: Repository, https://github.com/haripowesleyt/printly
Keywords: foreground color,background color,font style,color print
Classifier: Development Status :: 5 - Production/Stable
Classifier: Intended Audience :: Developers
Classifier: Programming Language :: Python :: 3.7
Classifier: Programming Language :: Python :: 3.8
Classifier: Programming Language :: Python :: 3.9
Classifier: Programming Language :: Python :: 3.10
Classifier: Programming Language :: Python :: 3.11
Classifier: Programming Language :: Python :: 3.12
Classifier: Programming Language :: Python :: 3.13
Classifier: License :: OSI Approved :: MIT License
Classifier: Operating System :: OS Independent
Requires-Python: >=3.7
License-File: LICENSE
Dynamic: license-file
